apojwt/ApoJWT.py
apojwt/__init__.py
apojwt-1.7.0.dist-info/LICENSE
apojwt-1.7.0.dist-info/METADATA
apojwt-1.7.0.dist-info/WHEEL
apojwt-1.7.0.dist-info/top_level.txt
apojwt-1.7.0.dist-info/RECORD
