Metadata-Version: 2.1
Name: apojwt
Version: 1.7.0
Summary: JWT Authentication Functions and Decorators. Built for Intent's Apogee Microservices
Author: Isaac Kuhlmann
License: Copyright 2022 In10t
Keywords: apojwt,jwt,apogee
Classifier: License :: OSI Approved :: BSD License
Classifier: Programming Language :: Python
Classifier: Programming Language :: Python :: 3
Requires-Python: >=3.6
License-File: LICENSE
Requires-Dist: PyJWT (>=2.0.0)
